grading_tools/__init__.py
grading_tools/from_cfg.py
grading_tools/main.py
grading_tools/write_schema.py
grading_tools/common/__init__.py
grading_tools/common/commands.py
grading_tools/common/compat_utils.py
grading_tools/common/defaults.py
grading_tools/common/excel_utils.py
grading_tools/common/gradable-spec-schema.yaml
grading_tools/common/gradable_spec.py
grading_tools/common/utils.py
grading_tools/diagram_gen/__init__.py
grading_tools/diagram_gen/diagrams.py
grading_tools/grading_table_gen/__init__.py
grading_tools/grading_table_gen/edit_grading_table.py
grading_tools/grading_table_gen/gen_grading_table.py
grading_tools/grading_table_gen/grading_table_commons.py
grading_tools/misc_table_gen/__init__.py
grading_tools/misc_table_gen/gen_assignment_groups_table.py
grading_tools/spec_manipulation/__init__.py
grading_tools/spec_manipulation/concat_gradable_specs.py
grading_tools/upload_export_gen/__init__.py
grading_tools/upload_export_gen/exam.py
grading_tools/upload_export_gen/group.py
grading_tools/upload_export_gen/group_feedback.py
pads_grading_tools-0.4.7.dist-info/METADATA
pads_grading_tools-0.4.7.dist-info/WHEEL
pads_grading_tools-0.4.7.dist-info/RECORD
