Metadata-Version: 2.4
Name: pads-grading-tools
Version: 0.4.7
Author-email: Leah Tacke genannt Unterberg <l.tgu@pads.rwth-aachen.de>
Requires-Python: >=3.12
Requires-Dist: jsonmerge<2,>=1.9.2
Requires-Dist: kaleido==0.2.1
Requires-Dist: matplotlib<4,>=3.9.2
Requires-Dist: openpyxl<4,>=3.1.5
Requires-Dist: pandas>=2.0
Requires-Dist: plotly<7,>=6.0.0
Requires-Dist: pydantic<3,>=2.11
Requires-Dist: pyyaml<7,>=6.0
Requires-Dist: xlsxwriter<4,>=3.2.0
